dateandtime/__init__.py
dateandtime/base.py
dateandtime/multicalendar.py
dateandtime/test_base.py
dateandtime/test_multicalendar.py
dateandtime-0.0.7.dist-info/DESCRIPTION.rst
dateandtime-0.0.7.dist-info/entry_points.txt
dateandtime-0.0.7.dist-info/METADATA
dateandtime-0.0.7.dist-info/metadata.json
dateandtime-0.0.7.dist-info/RECORD
dateandtime-0.0.7.dist-info/top_level.txt
dateandtime-0.0.7.dist-info/WHEEL
