Metadata-Version: 2.0
Name: dateandtime
Version: 0.0.7
Summary: A silly little text calendar application for your terminal
Home-page: https://github.com/a-tal/dateandtime
Author: Adam Talsma
Author-email: adam@talsma.ca
License: BSD
Download-URL: https://github.com/a-tal/dateandtime
Platform: UNKNOWN
Classifier: Development Status :: 5 - Production/Stable
Classifier: Environment :: Console
Classifier: Intended Audience :: System Administrators
Classifier: License :: OSI Approved :: BSD License
Classifier: Operating System :: POSIX :: Linux
Classifier: Programming Language :: Python
Requires-Dist: ddate (>=0.0.4)
